oarphpy/__init__.py
oarphpy/plotting.py
oarphpy/spark.py
oarphpy/util/__init__.py
oarphpy/util/archive_flyweight.py
oarphpy/util/log.py
oarphpy/util/misc.py
oarphpy/util/tfutil.py
oarphpy/util/thruput_observer.py
oarphpy-0.1.1.dist-info/DESCRIPTION.rst
oarphpy-0.1.1.dist-info/METADATA
oarphpy-0.1.1.dist-info/RECORD
oarphpy-0.1.1.dist-info/WHEEL
oarphpy-0.1.1.dist-info/metadata.json
oarphpy-0.1.1.dist-info/top_level.txt
