Metadata-Version: 2.0
Name: oarphpy
Version: 0.1.1
Summary: A collection of Python utils with an emphasis on Data Science
Home-page: https://github.com/pwais/oarphpy
Author: Oarph
Author-email: py@oarph.me
License: Apache License 2.0
Platform: UNKNOWN
Classifier: Development Status :: 4 - Beta
Classifier: Intended Audience :: Developers
Classifier: License :: OSI Approved :: Apache Software License
Classifier: Programming Language :: Python :: 2
Classifier: Programming Language :: Python :: 3
Classifier: Topic :: Software Development :: Libraries
Classifier: Topic :: Scientific/Engineering
Classifier: Topic :: System :: Distributed Computing
Provides-Extra: all
Provides-Extra: spark
Provides-Extra: tensorflow
Provides-Extra: utils
Provides-Extra: all
Requires-Dist: bokeh (==3.0.3); extra == 'all'
Requires-Dist: cloudpickle (>=1.5.0); extra == 'all'
Requires-Dist: cloudpickle (>=1.5.0); extra == 'all'
Requires-Dist: findspark (==1.3.0); extra == 'all'
Requires-Dist: humanfriendly; extra == 'all'
Requires-Dist: imageio; extra == 'all'
Requires-Dist: numpy; extra == 'all'
Requires-Dist: pandas (>=1.1.2); extra == 'all'
Requires-Dist: pandas (>=1.1.2); extra == 'all'
Requires-Dist: pyspark (>=3.0.1); extra == 'all'
Requires-Dist: six; extra == 'all'
Requires-Dist: tabulate; extra == 'all'
Requires-Dist: tabulatehelper; extra == 'all'
Provides-Extra: spark
Requires-Dist: cloudpickle (>=1.5.0); extra == 'spark'
Requires-Dist: findspark (==1.3.0); extra == 'spark'
Requires-Dist: numpy; extra == 'spark'
Requires-Dist: pandas (>=1.1.2); extra == 'spark'
Requires-Dist: pyspark (>=3.0.1); extra == 'spark'
Provides-Extra: tensorflow
Requires-Dist: crcmod; extra == 'tensorflow'
Provides-Extra: utils
Requires-Dist: bokeh (==3.0.3); extra == 'utils'
Requires-Dist: cloudpickle (>=1.5.0); extra == 'utils'
Requires-Dist: humanfriendly; extra == 'utils'
Requires-Dist: imageio; extra == 'utils'
Requires-Dist: pandas (>=1.1.2); extra == 'utils'
Requires-Dist: six; extra == 'utils'
Requires-Dist: tabulate; extra == 'utils'
Requires-Dist: tabulatehelper; extra == 'utils'
